magicbus/__init__.py
magicbus/base.py
magicbus/compat.py
magicbus/process.py
magicbus/win32.py
magicbus/plugins/__init__.py
magicbus/plugins/lifecycle.py
magicbus/plugins/loggers.py
magicbus/plugins/opsys.py
magicbus/plugins/servers.py
magicbus/plugins/signalhandler.py
magicbus/plugins/tasks.py
magicbus/test/__init__.py
magicbus/test/test_bus.py
magicbus/test/test_opsys.py
magicbus/test/test_processbus.py
magicbus/test/test_servers.py
magicbus/test/test_signals.py
magicbus/test/test_tasks.py
MagicBus-4.1.2.dist-info/LICENSE
MagicBus-4.1.2.dist-info/METADATA
MagicBus-4.1.2.dist-info/WHEEL
MagicBus-4.1.2.dist-info/namespace_packages.txt
MagicBus-4.1.2.dist-info/top_level.txt
MagicBus-4.1.2.dist-info/RECORD
