Metadata-Version: 2.1
Name: MagicBus
Version: 4.1.2
Summary: A pub/sub state machine
Home-page: https://github.com/cherrypy/MagicBus
Author: CherryPy Team
Author-email: team@cherrypy.org
License: UNKNOWN
Platform: UNKNOWN
Classifier: Development Status :: 3 - Alpha
Classifier: Environment :: Web Environment
Classifier: Intended Audience :: Developers
Classifier: License :: OSI Approved :: BSD License
Classifier: Operating System :: OS Independent
Classifier: Programming Language :: Python :: 2.7
Classifier: Programming Language :: Python :: 3
Classifier: Topic :: Internet :: WWW/HTTP
Classifier: Topic :: Internet :: WWW/HTTP :: HTTP Servers
Classifier: Topic :: Software Development :: Libraries :: Application Frameworks
Requires-Python: >=2.7
Provides-Extra: docs
Provides-Extra: testing
